Metadata-Version: 2.1
Name: cairo-kernel
Version: 0.0.6
Summary: Jupyter kernel for Cairo language
Home-page: UNKNOWN
Author: Ankit Chiplunkar, Arie Benhamou
Author-email: ankitchiplunkar@gmail.com, benhamou.arie@gmail.com
License: UNKNOWN
Keywords: ethereum,starkware
Platform: UNKNOWN
Classifier: Development Status :: 3 - Alpha
Classifier: Intended Audience :: Developers
Classifier: Natural Language :: English
Classifier: Programming Language :: Python :: 3
Classifier: Programming Language :: Python :: 3.6
Requires-Python: >=3.6, <3.10
